lusid_tr_sdk-0.5.1557.dist-info/DESCRIPTION.rst
lusid_tr_sdk-0.5.1557.dist-info/METADATA
lusid_tr_sdk-0.5.1557.dist-info/RECORD
lusid_tr_sdk-0.5.1557.dist-info/WHEEL
lusid_tr_sdk-0.5.1557.dist-info/metadata.json
lusid_tr_sdk-0.5.1557.dist-info/top_level.txt
lusidtr/__init__.py
lusidtr/lusid_tr.py
lusidtr/version.py
lusidtr/models/__init__.py
lusidtr/models/add_transaction_property_response.py
lusidtr/models/adjust_holding.py
lusidtr/models/adjust_holding_request.py
lusidtr/models/aggregate_spec.py
lusidtr/models/aggregation_request.py
lusidtr/models/aggregation_response_node.py
lusidtr/models/analytic_store.py
lusidtr/models/analytic_store_key.py
lusidtr/models/complete_portfolio.py
lusidtr/models/corporate_action.py
lusidtr/models/corporate_action_transition.py
lusidtr/models/corporate_action_transition_component.py
lusidtr/models/create_analytic_store_request.py
lusidtr/models/create_client_instrument_request.py
lusidtr/models/create_corporate_action.py
lusidtr/models/create_data_type_request.py
lusidtr/models/create_derived_transaction_portfolio_request.py
lusidtr/models/create_instrument_property_request.py
lusidtr/models/create_perpetual_property_request.py
lusidtr/models/create_portfolio_details.py
lusidtr/models/create_portfolio_group_request.py
lusidtr/models/create_property_definition_request.py
lusidtr/models/create_property_request.py
lusidtr/models/create_reference_portfolio_request.py
lusidtr/models/create_results.py
lusidtr/models/create_transaction_portfolio_request.py
lusidtr/models/create_unit_definition.py
lusidtr/models/currency_and_amount.py
lusidtr/models/data_type.py
lusidtr/models/delete_client_instruments_response.py
lusidtr/models/deleted_entity_response.py
lusidtr/models/error_detail.py
lusidtr/models/expanded_group.py
lusidtr/models/field_schema.py
lusidtr/models/holdings_adjustment.py
lusidtr/models/holdings_adjustment_header.py
lusidtr/models/instrument.py
lusidtr/models/instrument_analytic.py
lusidtr/models/instrument_definition.py
lusidtr/models/instrument_property.py
lusidtr/models/iunit_definition.py
lusidtr/models/key_value_pair_of_property_key_to_field_schema.py
lusidtr/models/link.py
lusidtr/models/list_aggregation_response.py
