Metadata-Version: 2.0
Name: lusid-tr-sdk
Version: 0.5.1557
Summary: Python SDK for LUSID TR API
Home-page: https://github.com/finbourne/lusid-sdk-python
Author: FINBOURNE Technology
Author-email: engineering@finbourne.com
License: MIT
Keywords: finbourne lusid
Platform: UNKNOWN
Classifier: Development Status :: 4 - Beta
Classifier: Intended Audience :: Developers
Classifier: Topic :: Software Development
Classifier: License :: OSI Approved :: MIT License
Classifier: Programming Language :: Python
Classifier: Programming Language :: Python :: 2.7
Classifier: Programming Language :: Python :: 3
Classifier: Programming Language :: Python :: 3.4
Classifier: Programming Language :: Python :: 3.5
Classifier: Programming Language :: Python :: 3.6
Requires-Dist: msrest (==0.4.26)
